{
  "project_info": {
    "project_number": "976940223966",
    "project_id": "poe22-4c6be",
    "storage_bucket": "poe22-4c6be.appspot.com"
  },
  "client": [
    {
      "client_info": {
        "mobilesdk_app_id": "1:976940223966:android:2e6bef685b5a313870e14f",
        "android_client_info": {
          "package_name": "com.example.poe22"
        }
      },
      "oauth_client": [],
      "api_key": [
        {
          "current_key": "AIzaSyDOv-gzrT-id6jsDTc5bkCfofgcqSiX28o"
        }
      ],
      "services": {
        "appinvite_service": {
          "other_platform_oauth_client": []
        }
      }
    }
  ],
  "configuration_version": "1"
}